mseep_mysql_mcp_server-1.0.2.dist-info/licenses/LICENSE
mysql_mcp_server/__init__.py
mysql_mcp_server/server.py
mseep_mysql_mcp_server-1.0.2.dist-info/METADATA
mseep_mysql_mcp_server-1.0.2.dist-info/WHEEL
mseep_mysql_mcp_server-1.0.2.dist-info/entry_points.txt
mseep_mysql_mcp_server-1.0.2.dist-info/top_level.txt
mseep_mysql_mcp_server-1.0.2.dist-info/RECORD
